core/__init__.py
core/abs_calculation_rule.py
core/admin.py
core/apps.py
core/custom_lookups.py
core/fields.py
core/forms.py
core/gql_queries.py
core/jwt.py
core/jwt_authentication.py
core/middleware.py
core/receivers.py
core/report.py
core/scheduler.py
core/schema.py
core/security.py
core/serializers.py
core/service_signals.py
core/signals.py
core/tasks.py
core/test_helpers.py
core/urls.py
core/utils.py
core/views.py
core/calendars/__init__.py
core/calendars/ad_calendar.py
core/calendars/ne_calendar.py
core/calendars/test_ad_calendar.py
core/calendars/test_ne_calendar.py
core/custom_filters/__init__.py
core/custom_filters/custom_filter_registry_point.py
core/custom_filters/custom_filter_wizard_interface.py
core/custom_filters/custom_filter_wizard_storage.py
core/data_masking/__init__.py
core/data_masking/abstract_mask.py
core/data_masking/masking_class_registry_point.py
core/data_masking/masking_class_storage.py
core/data_masking/masking_decorator.py
core/datetimes/__init__.py
core/datetimes/ad_datetime.py
core/datetimes/ne_datetime.py
core/datetimes/shared.py
core/datetimes/test_ad_datetime.py
core/datetimes/test_ne_datetime.py
core/datetimes/test_shared.py
core/gql/__init__.py
core/gql/custom_lookup.py
core/gql/export_mixin.py
core/gql/gql_mutations/__init__.py
core/gql/gql_mutations/base_mutation.py
core/gql/gql_mutations/exceptions.py
core/gql/gql_mutations/input_types.py
core/gql/gql_mutations/mutation_by_filter.py
core/migration_to_history_model/__init__.py
core/migration_to_history_model/create_temp_tables.py
core/migration_to_history_model/patch_table_data.py
core/migrations/0001_initial.py
core/migrations/0002_auto_20190726_0701.py
core/migrations/0003_control_mutationlog.py
core/migrations/0004_auto_20190830_1625.py
core/migrations/0005_group_usergroup.py
core/migrations/0006_fieldcontrol.py
core/migrations/0007_auto_20191008_0923.py
core/migrations/0008_officer_role_roleright_userrole.py
core/migrations/0009_mutationlog_client_mutation_details.py
openimis_be_core-1.10.0.dist-info/licenses/LICENSE.md
openimis_be_core-1.10.0.dist-info/METADATA
openimis_be_core-1.10.0.dist-info/WHEEL
openimis_be_core-1.10.0.dist-info/top_level.txt
openimis_be_core-1.10.0.dist-info/RECORD
