Metadata-Version: 2.4
Name: openimis-be-core
Version: 1.10.0
Summary: The openIMIS Backend Core reference module.
Home-page: https://openimis.org/
Author: Xavier Gillmann
Author-email: xgillmann@bluesquarehub.com
License: GNU AGPL v3
Classifier: Environment :: Web Environment
Classifier: Framework :: Django
Classifier: Framework :: Django :: 3.1
Classifier: Framework :: Django :: 3.2
Classifier: Intended Audience :: Developers
Classifier: License :: OSI Approved :: GNU Affero General Public License v3
Classifier: Operating System :: OS Independent
Classifier: Programming Language :: Python
Classifier: Programming Language :: Python :: 3.8
Classifier: Programming Language :: Python :: 3.9
Classifier: Programming Language :: Python :: 3.10
License-File: LICENSE.md
Requires-Dist: isodate
Requires-Dist: django
Requires-Dist: django-db-signals
Requires-Dist: djangorestframework
Requires-Dist: cached-property
Requires-Dist: nepalicalendar
Requires-Dist: django-simple-history
Requires-Dist: django-dirtyfields
Requires-Dist: websocket-client
Requires-Dist: jsonschema
Requires-Dist: password-validator
Requires-Dist: zxcvbn
Requires-Dist: django-ratelimit
Requires-Dist: pandas
Dynamic: author
Dynamic: author-email
Dynamic: classifier
Dynamic: home-page
Dynamic: license
Dynamic: license-file
Dynamic: requires-dist
Dynamic: summary
